django_db_counter/__init__.py
django_db_counter/admin.py
django_db_counter/apps.py
django_db_counter/models.py
django_db_counter/tests.py
django_db_counter/views.py
django_db_counter/locale/zh_Hans/LC_MESSAGES/django.mo
django_db_counter/locale/zh_Hans/LC_MESSAGES/django.po
django_db_counter/migrations/0001_initial.py
django_db_counter/migrations/__init__.py
django_db_counter-0.1.0.dist-info/LICENSE
django_db_counter-0.1.0.dist-info/METADATA
django_db_counter-0.1.0.dist-info/WHEEL
django_db_counter-0.1.0.dist-info/top_level.txt
django_db_counter-0.1.0.dist-info/RECORD
