Metadata-Version: 2.1
Name: django-db-counter
Version: 0.1.0
Summary: Obtain continuous count.
Home-page: UNKNOWN
Author: zencore
Author-email: dobetter@zencore.cn
License: MIT
Keywords: django,django model extensions
Platform: UNKNOWN
Classifier: Development Status :: 5 - Production/Stable
Classifier: Intended Audience :: Developers
Classifier: Topic :: Software Development :: Libraries :: Python Modules
Classifier: License :: OSI Approved :: MIT License
Classifier: Programming Language :: Python :: 3
Classifier: Programming Language :: Python :: 3 :: Only
License-File: LICENSE
Requires-Dist: django
